weirdgitter/__init__.py
weirdgitter/models.py
weirdgitter/utils.py
weirdgitter/weirdgitter.py
weirdgitter-0.0.5.dist-info/METADATA
weirdgitter-0.0.5.dist-info/WHEEL
weirdgitter-0.0.5.dist-info/licenses/LICENSE
weirdgitter-0.0.5.dist-info/RECORD
