Metadata-Version: 2.4
Name: WeirdGitter
Version: 0.0.5
Summary: Simple yet useful Continious Delivery script. Work with git and .sh/.bat scripts.
Author-email: Nikita Trubitsyn <nikitos99099@gmail.com>
License-File: LICENSE
Classifier: License :: OSI Approved :: GNU Lesser General Public License v3 (LGPLv3)
Classifier: Operating System :: OS Independent
Classifier: Programming Language :: Python :: 3
Requires-Python: >=3.9
